{
  "basics": {
    "name": "Julio Atz",
    "label": "Software Engineer | Quality Assurance Engineer",
    "image": "https://i.postimg.cc/d12mywTB/Clipped-image-20231210-11281687687.png",
    "email": "jatz93@outlook.com",
    "phone": "+50249805583",
    "url": "",
    "summary": "Analista y desarrollador de pruebas automatizadas, actualmente trabajo como ingeniero de aseguramiento de la calidad. He trabajo como desarrollador web full stack.",
    "location": {
      "address": "",
      "postalCode": "",
      "city": "Guatemala",
      "countryCode": "GT",
      "region": "Guatemala"
    },
    "profiles": [
      {
        "network": "Instagram",
        "username": "atzjulio",
        "url": "https://www.instagram.com/atzjulio"
      },
      {
        "network": "LinkedIn",
        "username": "Julio Atz",
        "url": "https://www.linkedin.com/in/jmfatzlopez"
      },
      {
        "network": "GitHub",
        "username": "jatz27",
        "url": "https://github.com/jatz27"
      }
    ]
  },
  "work": [
    {
      "name": "G&T Continental",
      "position": "Ingeniero de automatización de software",
      "url": "https://www.gtc.com.gt/",
      "startDate": "2025-04-22",
      "endDate": null,
      "summary": "Desarrollo y analicis de pruebas automatizadas para todos los aplicativos del banco G&T Continental para el ambiente de QA siendo ejecutadas desde Azure DevOps, para que esten disponibles los test de integración y funcionales. Adicionalmente, el uso de un servicio de integración continua para la automatización de la construcción de las aplicaciones, que se encarga de ejecutar los test de integración y funcionales; generar una imagen de Docker que se puede utilizar para desplegar las aplicaciones en Azure DevOps, con las tecnologias de HTML, CSS, TS, JS, SQL, JAVA (SELENIUM), TestNG, Angular, Appium (GTCApp), Docker y K6.",
      "highlights": [
        "Started the company"
      ]
    },
    {
      "name": "G&T Continental",
      "position": "Ingeniero de aseguramiento de la calidad",
      "url": "https://www.gtc.com.gt/",
      "startDate": "2023-05-09",
      "endDate": "2025-04-21",
      "summary": "Inspección de código, comunicación de endpoints, administración de base de datos y diseño web. En el área de aseguramiento de la calidad realicé pruebas y el lanzamiento de los siguientes proyectos: Apple Pay y onboardingTC. Actualmente me encuentro en el proyecto de migración del core bancario denominado DRACO, realizando pruebas integrales en transact T24, funcionales y no funcionales. Adicionalmente me encuentro capacitándome en el desarrollo de pruebas automatizadas con HTML, CSS, TS, JS, SQL, JAVA (SELENIUM), TestNG y Angular.",
      "highlights": [
        "Started the company"
      ]
    },
    {
      "name": "SAT",
      "position": "Analista y desarrollador",
      "url": "https://portal.sat.gob.gt/portal/",
      "startDate": "2021-02-12",
      "endDate": "2022-01-02",
      "summary": "Desarrollo de sistema de indicadores de comportamiento tributario utilizando las tecnologías: Oracle DB, Spring Boot, Maven, Primefaces, Apache Tomcat, Microservicios. Este desarrollo se utilizó para segmentar cada tipo de contribuyente y tener visibilidad de dónde provienen sus ingresos y gastos.",
      "highlights": [
        "Started the company"
      ]
    }
  ],
  "volunteer": [
    {
      "organization": "Organization",
      "position": "Volunteer",
      "url": "https://organization.com/",
      "startDate": "2012-01-01",
      "endDate": "2013-01-01",
      "summary": "Description…",
      "highlights": [
        "Awarded 'Volunteer of the Month'"
      ]
    }
  ],
  "education": [
    {
      "institution": "Universidad Mariano Galvez",
      "url": "https://institution.com/",
      "area": "Ingeniero en Sistamas de la Información",
      "studyType": "Ingeniero",
      "startDate": "2013-01-01",
      "endDate": "2018-01-01",
      "score": "4.0",
      "courses": [
        "DB1101 - Basic SQL"
      ]
    },
    {
      "institution": "Colegio CCEVSA",
      "url": "https://institution.com/",
      "area": "Bachillerato en Computación",
      "studyType": "Bachelor",
      "startDate": "2010-01-01",
      "endDate": "2011-01-01",
      "score": "4.0",
      "courses": [
        "DB1101 - Basic SQL"
      ]
    }
  ],
  "awards": [
    {
      "title": "Award",
      "date": "2014-11-01",
      "awarder": "Company",
      "summary": "There is no spoon."
    }
  ],
  "certificates": [
    {
      "name": "Certificate",
      "date": "2021-11-07",
      "issuer": "Company",
      "url": "https://certificate.com"
    }
  ],
  "publications": [
    {
      "name": "Publication",
      "publisher": "Company",
      "releaseDate": "2014-10-01",
      "url": "https://publication.com",
      "summary": "Description…"
    }
  ],
  "skills": [
    {
      "name": "HTML",
      "level": "Avanzado",
      "keywords": [
        "Desarrollo Web",
        "Frontend"
      ]
    },
    {
      "name": "CSS",
      "level": "Avanzado",
      "keywords": [
        "Desarrollo Web",
        "Frontend",
        "Diseño Responsive"
      ]
    },
    {
      "name": "JavaScript",
      "level": "Avanzado",
      "keywords": [
        "Desarrollo Web",
        "Frontend",
        "Backend",
        "Fullstack"
      ]
    },
    {
      "name": "TypeScript",
      "level": "Basico",
      "keywords": [
        "Desarrollo Web",
        "Frontend",
        "Backend",
        "JavaScript Superset"
      ]
    },
    {
      "name": "Java",
      "level": "Basico",
      "keywords": [
        "Desarrollo Web",
        "Frontend",
        "JavaScript Library",
        "UI"
      ]
    },
    {
      "name": "Node",
      "level": "Avanzado",
      "keywords": [
        "Desarrollo Web",
        "Backend",
        "JavaScript",
        "Servidor"
      ]
    },
    {
      "name": "MySQL",
      "level": "Avanzado",
      "keywords": [
        "Bases de Datos",
        "SQL",
        "Almacenamiento de Datos",
        "Backend"
      ]
    },
    {
      "name": "SQLServer",
      "level": "Avanzado",
      "keywords": [
        "Bases de Datos",
        "SQL",
        "Almacenamiento de Datos",
        "Backend"
      ]
    },
    {
      "name": "Git",
      "level": "Avanzado",
      "keywords": [
        "Control de Versiones",
        "Colaboración",
        "Código Fuente"
      ]
    },
    {
      "name": "GitHub",
      "level": "Avanzado",
      "keywords": [
        "Control de Versiones",
        "Colaboración",
        "Código Fuente",
        "Git"
      ]
    },
    {
      "name": "React",
      "level": "Basico",
      "keywords": [
        "Desarrollo Web",
        "Frontend",
        "JavaScript Library",
        "UI"
      ]
    },
    {
      "name": "Docker",
      "level": "Basico",
      "keywords": [
        "Conenedores",
        "DevOps",
        "Backend",
        ""
      ]
    },
    {
      "name": "Selenium",
      "level": "Basico",
      "keywords": [
        "Automatizacion",
        "Web",
        "Frontend",
        ""
      ]
    },
    {
      "name": "Angular",
      "level": "Basico",
      "keywords": [
        "Frontend",
        "JavaScript Library",
        "UI",
        ""
      ]
    }
  ],
  "languages": [
    {
      "language": "English",
      "fluency": "Native speaker"
    }
  ],
  "interests": [
    {
      "name": "Wildlife",
      "keywords": [
        "Ferrets",
        "Unicorns"
      ]
    }
  ],
  "references": [
    {
      "name": "Jane Doe",
      "reference": "Reference…"
    }
  ],
  "projects": [
    {
      "name": "Ambiente de desarrollo",
      "isActive": false,
      "description": "Configuración de ambiente de desarrollo para el proyectos",
      "highlights": [
        "Neovim",
        "PWSH",
        "Terminal"
      ],
      "url": "https://github.com/jatz27/dotfiles.config",
      "github": "https://github.com/jatz27/dotfiles.config"
    },
    {
      "name": "Proyecto portafolio web y CV",
      "isActive": false,
      "description": "Proyecto dessarollado en Astro configurado desde un json para proveer toda la infomación necesaria para el CV y el portafolio web",
      "highlights": [
        "Astro",
        "JavaScript",
        "JSON"
      ],
      "url": "https://github.com/jatz27/portfolio",
      "github": "https://github.com/jatz27/portfolio"
    }
  ]
}